obdiag_mcp/__init__.py
obdiag_mcp/__main__.py
obdiag_mcp/server.py
obdiag_mcp-0.0.3.dist-info/licenses/LICENSE
obdiag_mcp-0.0.3.dist-info/METADATA
obdiag_mcp-0.0.3.dist-info/WHEEL
obdiag_mcp-0.0.3.dist-info/entry_points.txt
obdiag_mcp-0.0.3.dist-info/top_level.txt
obdiag_mcp-0.0.3.dist-info/RECORD
