Metadata-Version: 2.4
Name: obdiag-mcp
Version: 0.0.3
Summary: OBDiag MCP Server - Model Context Protocol server for OceanBase Diagnostic Tool
Home-page: https://github.com/oceanbase/mcp-oceanbase
Author: OceanBase
Author-email: OceanBase <support@oceanbase.com>
Maintainer-email: OceanBase <support@oceanbase.com>
License: Apache-2.0
Project-URL: Bug Reports, https://github.com/oceanbase/mcp-oceanbase/issues
Project-URL: Source, https://github.com/oceanbase/mcp-oceanbase
Project-URL: Documentation, https://www.oceanbase.com/docs
Project-URL: Community, https://ask.oceanbase.com
Keywords: oceanbase,obdiag,mcp,diagnostic,database,monitoring
Classifier: Development Status :: 3 - Alpha
Classifier: Intended Audience :: Developers
Classifier: Intended Audience :: System Administrators
Classifier: Operating System :: OS Independent
Classifier: Programming Language :: Python :: 3
Classifier: Programming Language :: Python :: 3.10
Classifier: Topic :: Database
Classifier: Topic :: System :: Monitoring
Classifier: Topic :: Software Development :: Libraries :: Python Modules
Requires-Python: >=3.10
License-File: LICENSE
Requires-Dist: fastmcp>=1.0
Requires-Dist: uvicorn>=0.27.1
Requires-Dist: tomli>=1.2.0; python_version < "3.11"
Provides-Extra: dev
Requires-Dist: pytest>=7.0.0; extra == "dev"
Requires-Dist: pytest-asyncio>=0.21.0; extra == "dev"
Requires-Dist: black>=22.0.0; extra == "dev"
Requires-Dist: flake8>=4.0.0; extra == "dev"
Requires-Dist: mypy>=0.991; extra == "dev"
Requires-Dist: build>=0.10.0; extra == "dev"
Requires-Dist: twine>=4.0.0; extra == "dev"
Provides-Extra: test
Requires-Dist: pytest>=7.0.0; extra == "test"
Requires-Dist: pytest-asyncio>=0.21.0; extra == "test"
Requires-Dist: pytest-cov>=4.0.0; extra == "test"
Dynamic: author
Dynamic: home-page
Dynamic: license-file
Dynamic: requires-python
